NyxUtils/__init__.py
NyxUtils/advanced_utils.py
NyxUtils/datetime_utils.py
NyxUtils/encoding_utils.py
NyxUtils/file_utils.py
NyxUtils/json_utils.py
NyxUtils/logger_utils.py
NyxUtils/math_utils.py
NyxUtils/nyx_advanced.py
NyxUtils/nyx_datetime.py
NyxUtils/nyx_encoding.py
NyxUtils/nyx_file.py
NyxUtils/nyx_id_generator.py
NyxUtils/nyx_json.py
NyxUtils/nyx_logger.py
NyxUtils/nyx_math.py
NyxUtils/nyx_progress_bar.py
NyxUtils/nyx_regex.py
NyxUtils/nyx_sqllite.py
NyxUtils/nyx_string.py
NyxUtils/nyx_system.py
NyxUtils/progress_bar_utils.py
NyxUtils/regex_utils.py
NyxUtils/string_utils.py
NyxUtils/system_utils.py
NyxUtils-0.1.2.dist-info/METADATA
NyxUtils-0.1.2.dist-info/WHEEL
NyxUtils-0.1.2.dist-info/top_level.txt
NyxUtils-0.1.2.dist-info/RECORD
