Metadata-Version: 2.2
Name: NyxUtils
Version: 0.1.2
Summary: A utility package providing various helpful functions.
Home-page: https://github.com/yourusername/NyxUtils
Author: AlitaZzz
Classifier: Programming Language :: Python :: 3
Classifier: License :: OSI Approved :: MIT License
Classifier: Operating System :: OS Independent
Requires-Python: >=3.6
Requires-Dist: aiosqlite
Requires-Dist: requests
Dynamic: author
Dynamic: classifier
Dynamic: home-page
Dynamic: requires-dist
Dynamic: requires-python
Dynamic: summary
